Metadata-Version: 2.1
Name: hamapi
Version: 0.1.10
Summary: HAM Systems API
Home-page: UNKNOWN
Author: Lefteris Chatzipetrou
Author-email: lefteris@hamsystems.eu
License: UNKNOWN
Platform: UNKNOWN
Classifier: Programming Language :: Python :: 3
Classifier: License :: OSI Approved :: MIT License
Classifier: Operating System :: OS Independent
Requires-Python: >=3.6
License-File: LICENSE
